flask_cognito_lib_custom/__init__.py
flask_cognito_lib_custom/config.py
flask_cognito_lib_custom/decorators.py
flask_cognito_lib_custom/exceptions.py
flask_cognito_lib_custom/plugin.py
flask_cognito_lib_custom/services/__init__.py
flask_cognito_lib_custom/services/cognito_svc.py
flask_cognito_lib_custom/services/token_svc.py
flask_cognito_lib_custom/utils.py
flask_cognito_lib_custom-1.8.2rc3.dist-info/LICENSE
flask_cognito_lib_custom-1.8.2rc3.dist-info/METADATA
flask_cognito_lib_custom-1.8.2rc3.dist-info/WHEEL
flask_cognito_lib_custom-1.8.2rc3.dist-info/RECORD
