Metadata-Version: 2.1
Name: flask_cognito_lib_custom
Version: 1.8.2rc3
Summary: A Flask extension that supports protecting routes with AWS Cognito following OAuth 2.1 best practices
Home-page: https://github.com/mblackgeo/flask-cognito-lib
License: MIT
Keywords: Flask,Extension,OAuth,Cognito
Author: mblackgeo
Author-email: 18327836+mblackgeo@users.noreply.github.com
Requires-Python: >=3.8,<4.0
Classifier: Environment :: Web Environment
Classifier: Framework :: Flask
Classifier: Intended Audience :: Developers
Classifier: License :: OSI Approved :: MIT License
Classifier: Operating System :: OS Independent
Classifier: Programming Language :: Python :: 3
Classifier: Programming Language :: Python :: 3.8
Classifier: Programming Language :: Python :: 3.9
Classifier: Programming Language :: Python :: 3.10
Classifier: Programming Language :: Python :: 3.11
Classifier: Programming Language :: Python :: 3.12
Classifier: Topic :: Internet :: WWW/HTTP :: Dynamic Content
Classifier: Topic :: Internet :: WWW/HTTP :: WSGI
Classifier: Topic :: Internet :: WWW/HTTP :: WSGI :: Middleware
Classifier: Topic :: Software Development :: Libraries :: Python Modules
Classifier: Typing :: Typed
Requires-Dist: Flask (>=2.0,<4.0)
Requires-Dist: PyJWT[crypto] (>=2.4,<3.0)
Requires-Dist: cryptography (>=42.0.4,<43.0.0)
Requires-Dist: requests (>=2.0,<3.0)
Requires-Dist: urllib3 (<3.0)
Project-URL: Repository, https://github.com/mblackgeo/flask-cognito-lib
